full_adder_nbit/rtl/half_adder.v
module half_adder(
	input wire a,
	input wire b,
	output wire sum,
	output wire carry
);

	assign sum = a ^ b;
	assign carry =  a & b;

endmodule

full_adder_nbit/rtl/full_adder.v
module full_adder (
	input wire a,
	input wire b,
	input wire cin,
	output wire sum,
	output wire carry
);

	wire sum1, carry1, carry2;

	half_adder ha1 (.a(a), .b(b), .sum(sum1), .carry(carry1));
	half_adder ha2 (.a(sum1), .b(cin), .sum(sum), .carry(carry2));

	assign carry = carry1 | carry2;

endmodule

full_adder_nbit/rtl/top.v
module full_adder_nbit #(parameter N = 8) (
	input wire [N - 1 : 0] a,
	input wire [N - 1 : 0] b,
	output reg [N - 1 : 0] sum,
	output reg cout
);

wire [N - 1: 0] carry_internal;
wire [N - 1: 0] sum_internal;

genvar i;

initial begin
	if (N < 2 || N > 32) begin
		$display("-------------------------------------------------------------------------");
		$display("-----------------ERROR: N out of range (1 < N < 33)----------------------");
		$display("-------------------------------------------------------------------------");
	end
end
generate
	for (i = 0; i < N; i = i + 1) begin
		if (i == 0) begin
			full_adder ic (.a(a[i]), .b(b[i]), .cin(1'b0), .sum(sum_internal[i]), .carry(carry_internal[i]));
		end else begin
			full_adder ic (.a(a[i]), .b(b[i]), .cin(carry_internal[i-1]), .sum(sum_internal[i]), .carry(carry_internal[i]));
		end
	end
endgenerate

always @(*) begin
	sum = sum_internal;
	cout = carry_internal[N-1];
end

endmodule

full_adder_nbit/tb/test_bench.v
`timescale 1ns/1ps
module test_bench;
	parameter N = 8;

	reg [N - 1 : 0] a;
	reg [N - 1 : 0] b;
	wire [N - 1 : 0] sum;
	wire cout;

	full_adder_nbit #(N) dut (
		.a(a),
		.b(b),
		.sum(sum),
		.cout(cout)
	);

	integer i;

	initial begin
		$dumpfile("test_bench.vcd");
		$dumpvars(0, test_bench);
		
		$display("-------------------------------------------------------------------------------------------------");
		$display("-------------------------------TESTBENCH FOR FULL ADDER %D BIT-----------------------------------",N);
		$display("-------------------------------------------------------------------------------------------------");
		
		for (i = 0; i < 100; i = i + 1) begin
			a = $random % (1 << N);
			b = $random % (1 << N);
			#1;
			check_result(calc_expected(a,b));
			#10;
		end
		

	end

	function [N : 0] calc_expected (input [N - 1 : 0] a_val, input [N - 1 : 0] b_val);
		begin
			calc_expected = a_val + b_val;
		end
	endfunction

	task check_result(input [N : 0] expected_result);
		begin
			 $display("At time: %t, a =%b, b = %b",$time, a, b);
			 if (sum == expected_result[N - 1: 0] && cout == expected_result[N]) begin
				 $display("-------------------------------------------------------------------------------------------------");
				 $display("PASSED: Expected_sum: %b, Got_sum: %b, Expected_cout: 1'b%b, Got_cout: 1'b%b", expected_result[N - 1 : 0], sum, expected_result[N], cout);
				 $display("-------------------------------------------------------------------------------------------------");
			 end else begin
				 $display("-------------------------------------------------------------------------------------------------");
				 $display("FAILED: Expected_sum: %b, Got_sum: %b, Expected_cout: 1'b%b, Got_cout: 1'b%b", expected_result[N - 1 : 0], sum, expected_result[N], cout);
				 $display("-------------------------------------------------------------------------------------------------");
			 end
		 end
	 endtask
endmodule

full_adder_nbit/sim/test_bench.vcd
$date
	Sat Dec 21 14:54:57 2024
$end
$version
	Icarus Verilog
$end
$timescale
	1ps
$end
$scope module test_bench $end
$var wire 8 ! sum [7:0] $end
$var wire 1 " cout $end
$var parameter 32 # N $end
$var reg 8 $ a [7:0] $end
$var reg 8 % b [7:0] $end
$var integer 32 & i [31:0] $end
$scope function calc_expected $end
$var reg 8 ' a_val [7:0] $end
$var reg 8 ( b_val [7:0] $end
$upscope $end
$scope module dut $end
$var wire 8 ) a [7:0] $end
$var wire 8 * b [7:0] $end
$var wire 8 + sum_internal [7:0] $end
$var wire 8 , carry_internal [7:0] $end
$var parameter 32 - N $end
$var reg 1 " cout $end
$var reg 8 . sum [7:0] $end
$scope begin genblk1[0] $end
$var parameter 2 / i $end
$scope begin genblk1 $end
$scope module ic $end
$var wire 1 0 a $end
$var wire 1 1 b $end
$var wire 1 2 carry $end
$var wire 1 3 cin $end
$var wire 1 4 sum1 $end
$var wire 1 5 sum $end
$var wire 1 6 carry2 $end
$var wire 1 7 carry1 $end
$scope module ha1 $end
$var wire 1 0 a $end
$var wire 1 1 b $end
$var wire 1 7 carry $end
$var wire 1 4 sum $end
$upscope $end
$scope module ha2 $end
$var wire 1 4 a $end
$var wire 1 3 b $end
$var wire 1 6 carry $end
$var wire 1 5 sum $end
$upscope $end
$upscope $end
$upscope $end
$upscope $end
$scope begin genblk1[1] $end
$var parameter 2 8 i $end
$scope begin genblk1 $end
$scope module ic $end
$var wire 1 9 a $end
$var wire 1 : b $end
$var wire 1 ; carry $end
$var wire 1 < cin $end
$var wire 1 = sum1 $end
$var wire 1 > sum $end
$var wire 1 ? carry2 $end
$var wire 1 @ carry1 $end
$scope module ha1 $end
$var wire 1 9 a $end
$var wire 1 : b $end
$var wire 1 @ carry $end
$var wire 1 = sum $end
$upscope $end
$scope module ha2 $end
$var wire 1 = a $end
$var wire 1 < b $end
$var wire 1 ? carry $end
$var wire 1 > sum $end
$upscope $end
$upscope $end
$upscope $end
$upscope $end
$scope begin genblk1[2] $end
$var parameter 3 A i $end
$scope begin genblk1 $end
$scope module ic $end
$var wire 1 B a $end
$var wire 1 C b $end
$var wire 1 D carry $end
$var wire 1 E cin $end
$var wire 1 F sum1 $end
$var wire 1 G sum $end
$var wire 1 H carry2 $end
$var wire 1 I carry1 $end
$scope module ha1 $end
$var wire 1 B a $end
$var wire 1 C b $end
$var wire 1 I carry $end
$var wire 1 F sum $end
$upscope $end
$scope module ha2 $end
$var wire 1 F a $end
$var wire 1 E b $end
$var wire 1 H carry $end
$var wire 1 G sum $end
$upscope $end
$upscope $end
$upscope $end
$upscope $end
$scope begin genblk1[3] $end
$var parameter 3 J i $end
$scope begin genblk1 $end
$scope module ic $end
$var wire 1 K a $end
$var wire 1 L b $end
$var wire 1 M carry $end
$var wire 1 N cin $end
$var wire 1 O sum1 $end
$var wire 1 P sum $end
$var wire 1 Q carry2 $end
$var wire 1 R carry1 $end
$scope module ha1 $end
$var wire 1 K a $end
$var wire 1 L b $end
$var wire 1 R carry $end
$var wire 1 O sum $end
$upscope $end
$scope module ha2 $end
$var wire 1 O a $end
$var wire 1 N b $end
$var wire 1 Q carry $end
$var wire 1 P sum $end
$upscope $end
$upscope $end
$upscope $end
$upscope $end
$scope begin genblk1[4] $end
$var parameter 4 S i $end
$scope begin genblk1 $end
$scope module ic $end
$var wire 1 T a $end
$var wire 1 U b $end
$var wire 1 V carry $end
$var wire 1 W cin $end
$var wire 1 X sum1 $end
$var wire 1 Y sum $end
$var wire 1 Z carry2 $end
$var wire 1 [ carry1 $end
$scope module ha1 $end
$var wire 1 T a $end
$var wire 1 U b $end
$var wire 1 [ carry $end
$var wire 1 X sum $end
$upscope $end
$scope module ha2 $end
$var wire 1 X a $end
$var wire 1 W b $end
$var wire 1 Z carry $end
$var wire 1 Y sum $end
$upscope $end
$upscope $end
$upscope $end
$upscope $end
$scope begin genblk1[5] $end
$var parameter 4 \ i $end
$scope begin genblk1 $end
$scope module ic $end
$var wire 1 ] a $end
$var wire 1 ^ b $end
$var wire 1 _ carry $end
$var wire 1 ` cin $end
$var wire 1 a sum1 $end
$var wire 1 b sum $end
$var wire 1 c carry2 $end
$var wire 1 d carry1 $end
$scope module ha1 $end
$var wire 1 ] a $end
$var wire 1 ^ b $end
$var wire 1 d carry $end
$var wire 1 a sum $end
$upscope $end
$scope module ha2 $end
$var wire 1 a a $end
$var wire 1 ` b $end
$var wire 1 c carry $end
$var wire 1 b sum $end
$upscope $end
$upscope $end
$upscope $end
$upscope $end
$scope begin genblk1[6] $end
$var parameter 4 e i $end
$scope begin genblk1 $end
$scope module ic $end
$var wire 1 f a $end
$var wire 1 g b $end
$var wire 1 h carry $end
$var wire 1 i cin $end
$var wire 1 j sum1 $end
$var wire 1 k sum $end
$var wire 1 l carry2 $end
$var wire 1 m carry1 $end
$scope module ha1 $end
$var wire 1 f a $end
$var wire 1 g b $end
$var wire 1 m carry $end
$var wire 1 j sum $end
$upscope $end
$scope module ha2 $end
$var wire 1 j a $end
$var wire 1 i b $end
$var wire 1 l carry $end
$var wire 1 k sum $end
$upscope $end
$upscope $end
$upscope $end
$upscope $end
$scope begin genblk1[7] $end
$var parameter 4 n i $end
$scope begin genblk1 $end
$scope module ic $end
$var wire 1 o a $end
$var wire 1 p b $end
$var wire 1 q carry $end
$var wire 1 r cin $end
$var wire 1 s sum1 $end
$var wire 1 t sum $end
$var wire 1 u carry2 $end
$var wire 1 v carry1 $end
$scope module ha1 $end
$var wire 1 o a $end
$var wire 1 p b $end
$var wire 1 v carry $end
$var wire 1 s sum $end
$upscope $end
$scope module ha2 $end
$var wire 1 s a $end
$var wire 1 r b $end
$var wire 1 u carry $end
$var wire 1 t sum $end
$upscope $end
$upscope $end
$upscope $end
$upscope $end
$upscope $end
$scope task check_result $end
$var reg 9 w expected_result [8:0] $end
$upscope $end
$upscope $end
$enddefinitions $end
$comment Show the parameter values. $end
$dumpall
b111 n
b110 e
b101 \
b100 S
b11 J
b10 A
b1 8
b0 /
b1000 -
b1000 #
$end
#0
$dumpvars
bx w
0v
0u
1t
1s
0r
0q
1p
0o
0m
0l
0k
0j
0i
0h
0g
0f
0d
0c
1b
1a
0`
0_
0^
1]
0[
0Z
0Y
0X
0W
0V
0U
0T
0R
0Q
0P
0O
0N
0M
0L
0K
0I
0H
1G
1F
0E
0D
0C
1B
0@
0?
0>
0=
0<
0;
0:
09
07
06
15
14
03
02
11
00
b10100101 .
b0 ,
b10100101 +
b10000001 *
b100100 )
bx (
bx '
b0 &
b10000001 %
b100100 $
0"
b10100101 !
$end
#1000
b10100101 w
b100100 '
b10000001 (
#11000
1E
1;
1?
1<
b1101100 !
b1101100 .
0>
1k
0t
05
b11 ,
12
1G
b1101100 +
1P
1=
1j
0s
04
17
0F
1O
1:
1^
1g
0p
10
0B
1K
0]
b1100011 %
b1100011 *
b1001 $
b1001 )
b1 &
#12000
b1101100 w
b1001 '
b1100011 (
#22000
0G
0E
1Y
0;
1W
1N
b10011010 !
b10011010 .
1>
0?
1P
1M
0b
0k
b10011010 +
1t
b1101 ,
1D
0=
0O
1R
0a
0j
1s
1I
0:
1C
1L
0^
0g
1p
1B
b10001101 %
b10001101 *
b1101 $
b1101 )
b10 &
#23000
b10011010 w
b1101 '
b10001101 (
#33000
0r
0h
0l
0i
0_
0H
0c
0E
0P
0`
0<
0;
0N
0V
0W
b1110111 !
b1110111 .
15
02
1>
0?
1G
0D
1Y
0Z
0t
b0 ,
0M
1b
b1110111 +
1k
14
07
1=
1F
0I
1X
0s
0R
1a
1j
01
1:
0C
0L
1U
0p
0K
1]
1f
b10010 %
b10010 *
b1100101 $
b1100101 )
b11 &
#34000
b1110111 w
b1100101 '
b10010 (
#44000
1<
b1110 !
b1110 .
05
b1 ,
12
1>
1P
0Y
0b
b1110 +
0k
04
17
0=
1O
0X
0a
0j
11
0:
1C
1L
0U
0B
0]
0f
b1101 %
b1101 *
b1 $
b1 )
b100 &
#45000
b1110 w
b1 '
b1101 (
#55000
1Y
1t
1W
1r
1M
1h
0E
0P
1Q
1b
1l
0<
0;
1N
1`
1i
b10110011 !
b10110011 .
15
02
1>
0?
0G
1D
1V
b1111100 ,
1_
b10110011 +
0k
14
07
1=
0F
1I
1[
1d
1j
1U
1^
00
19
1B
1T
1]
1f
b111101 %
b111101 *
b1110110 $
b1110110 )
b101 &
#56000
b10110011 w
b1110110 '
b111101 (
#66000
0t
0r
0h
1k
0l
0i
0`
1"
b1111001 !
b1111001 .
1b
0c
0_
0>
b1111001 +
1P
0Q
0V
b10001100 ,
1q
1a
0d
0=
0O
1R
0[
1v
01
0U
0^
1p
10
09
1K
0T
1o
b10001100 %
b10001100 *
b11101101 $
b11101101 )
b110 &
#67000
b101111001 w
b11101101 '
b10001100 (
#77000
0i
0_
1b
0c
1t
0`
0W
1r
0N
b10111111 !
b10111111 .
0V
1>
1P
0Q
0M
0k
1h
1G
b11000000 ,
0D
b10111111 +
1Y
0Z
1=
1O
0R
0j
1m
1F
0I
1X
1:
0L
1g
0B
1T
b11000110 %
b11000110 *
b11111001 $
b11111001 )
b111 &
#78000
b110111111 w
b11111001 '
b11000110 (
#88000
0t
0r
b1101111 !
b1101111 .
1k
b10000000 ,
0h
b1101111 +
0Y
1j
0m
0X
0C
1L
1^
0g
1B
0K
0T
0]
b10101010 %
b10101010 *
b11000101 $
b11000101 )
b1000 &
#89000
b101101111 w
b11000101 '
b10101010 (
#99000
1E
1;
0>
1?
1u
1<
1N
1r
1i
1"
b1011100 !
b1011100 .
05
12
1G
1D
1P
1Y
1k
1h
0t
1q
b1011100 +
0b
b11100111 ,
1_
04
17
0F
1I
0O
1X
0j
1m
1s
0v
0a
1d
11
1C
0L
1U
1g
0p
1]
b1110111 %
b1110111 *
b11100101 $
b11100101 )
b1001 &
#100000
b101011100 w
b11100101 '
b1110111 (
#110000
1b
1`
1V
0Y
1Z
0"
0q
1W
0k
1t
0u
1M
0<
1N
0i
0r
b10100001 !
b10100001 .
0P
1Q
15
02
0>
0?
b10100001 +
0G
1H
1D
0_
b11110 ,
0h
1O
14
07
0=
1@
1F
0I
0d
0m
1L
0U
0^
0g
1p
00
19
0B
1T
0]
0f
0o
b10001111 %
b10001111 *
b10010 $
b10010 )
b1010 &
#111000
b10100001 w
b10010 '
b10001111 (
#121000
1k
1i
1_
1r
1"
b11000000 !
b11000000 .
05
0b
1c
1h
b11000000 +
1t
b11111110 ,
1q
04
1a
1m
0s
1v
01
1g
1]
1f
1o
b11001110 %
b11001110 *
b11110010 $
b11110010 )
b1011 &
#122000
b111000000 w
b11110010 '
b11001110 (
#132000
0W
0M
0k
1P
0Q
0i
0N
0_
0D
1b
0c
1G
0H
0`
0E
b10101101 !
b10101101 .
0V
15
b11000000 ,
0;
b10101101 +
0Y
0Z
14
0@
0X
11
0:
0L
09
1K
0T
b11000101 %
b11000101 *
b11101000 $
b11101000 )
b1100 &
#133000
b110101101 w
b11101000 '
b11000101 (
#143000
1l
1i
1_
1Y
0b
1c
1W
1r
1N
1`
1"
b11001 !
b11001 .
1P
1M
0k
1h
0G
1D
1V
b11001 +
0t
1u
b11111100 ,
1q
0O
1R
1j
0m
0F
1I
1[
1s
0v
1L
1U
1^
0g
1B
1T
0]
0o
b10111101 %
b10111101 *
b1011100 $
b1011100 )
b1101 &
#144000
b100011001 w
b1011100 '
b10111101 (
#154000
1Y
0"
1>
1W
0q
1<
0`
b10010010 !
b10010010 .
0P
1Q
1M
1t
0u
05
12
b1101101 ,
0V
b10010010 +
0b
0c
1O
0R
0s
04
17
0[
0a
1d
0L
0U
1g
0p
10
0T
1]
0f
b1100101 %
b1100101 *
b101101 $
b101101 )
b1110 &
#155000
b10010010 w
b101101 '
b1100101 (
#165000
0t
0Y
0r
0W
0h
0M
0>
1k
0l
1G
1P
0Q
0<
0i
1E
0N
b1101101 !
b1101101 .
15
02
b1101101 +
1b
0_
1;
b10 ,
0D
14
07
1a
0d
1@
0I
01
1:
0C
1L
0^
0g
19
0B
0K
1f
b1010 %
b1010 *
b1100011 $
b1100011 )
b1111 &
#166000
b1101101 w
b1100011 '
b1010 (
#176000
0G
0E
b10100000 !
b10100000 .
0P
05
b0 ,
0;
0k
b10100000 +
1t
0O
04
0@
0j
1s
0:
0L
1^
00
09
0]
0f
1o
b100000 %
b100000 *
b10000000 $
b10000000 )
b10000 &
#177000
b10100000 w
b10000000 '
b100000 (
#187000
1k
1i
1_
0b
1c
1`
1V
1Z
1W
1"
b1000111 !
b1000111 .
15
1G
0Y
0t
1q
b1000111 +
1>
b10111000 ,
1M
14
1F
1X
0s
1v
1=
1R
11
1C
1L
1U
0^
1p
19
1K
1]
b10011101 %
b10011101 *
b10101010 $
b10101010 )
b10001 &
#188000
b101000111 w
b10101010 '
b10011101 (
#198000
1P
1N
1D
0k
0G
1H
0i
1E
0W
0"
b10101001 !
b10101001 .
0_
0>
1;
1t
0q
b10110 ,
0M
0Y
0Z
b10101001 +
1b
0c
0=
1@
1s
0v
0R
0X
1[
0a
1:
0C
0L
0p
1B
0K
1T
0]
b10011 %
b10011 *
b10010110 $
b10010110 )
b10010 &
#199000
b10101001 w
b10010110 '
b10011 (
#209000
1N
1D
1Z
1?
0G
1H
1W
1b
1<
1E
1M
1`
b1100000 !
b1100000 .
1k
05
12
0>
1;
0P
1Q
0Y
b11111 ,
1V
b1100000 +
0t
1j
04
17
1=
0@
1O
1X
0[
0s
1g
10
09
1K
0T
0o
b1010011 %
b1010011 *
b1101 $
b1101 )
b10011 &
#210000
b1100000 w
b1101 '
b1010011 (
#220000
1"
1q
1i
1u
1_
1r
b1000000 !
b1000000 .
0t
0b
1c
b1000000 +
1k
b11111111 ,
1h
1s
1a
0j
1m
0:
1C
1p
19
0B
1]
1f
b11010101 %
b11010101 *
b1101011 $
b1101011 )
b10100 &
#221000
b101000000 w
b1101011 '
b11010101 (
#231000
0k
0i
0_
0"
1b
0c
0q
0`
1t
0u
0V
0<
0r
b10110000 !
b10110000 .
0>
0?
b10110000 +
1Y
0Z
02
b1110 ,
0h
0=
1@
0X
07
0m
01
1:
1L
0U
1^
0g
00
0K
0]
0f
b10101110 %
b10101110 *
b10 $
b10 )
b10101 &
#232000
b10110000 w
b10 '
b10101110 (
#242000
1?
1`
1<
1E
b11101100 !
b11101100 .
1V
1b
1k
12
0>
b11111 ,
1;
1G
0H
1P
0Q
b11101100 +
0Y
1Z
0a
1j
17
1=
0@
0F
1I
0O
1R
1X
11
0^
1g
10
09
1B
1K
1T
b11001111 %
b11001111 *
b11101 $
b11101 )
b10110 &
#243000
b11101100 w
b11101 '
b11001111 (
#253000
0`
0i
0<
0N
0W
0V
b101101 !
b101101 .
0_
15
02
0k
0t
0>
0?
0D
1P
0Q
b10 ,
0M
0Y
0Z
b101101 +
1b
0c
14
07
0j
0s
0=
1@
0I
1O
0R
0X
1a
01
0C
0g
0p
19
0B
0K
0T
1]
b1010 %
b1010 *
b100011 $
b100011 )
b10111 &
#254000
b101101 w
b100011 '
b1010 (
#264000
1"
1q
1u
1r
1h
1l
1i
1_
0b
1c
1`
1V
0N
1Z
0E
0D
1W
b110 !
b110 .
1>
0;
1G
0H
0Y
05
0P
b11111000 ,
1M
0k
b110 +
0t
1=
0@
1F
1X
04
0O
1R
1j
1s
0:
1C
1U
1^
00
1K
0]
1f
1o
b111100 %
b111100 *
b11001010 $
b11001010 )
b11000 &
#265000
b100000110 w
b11001010 '
b111100 (
#275000
0r
0h
1k
0l
0i
0_
1b
0c
0`
0V
1Y
0Z
1E
0W
b1111100 !
b1111100 .
0>
1;
1G
0t
0u
b1111100 +
1P
b10000010 ,
0M
0=
1@
0F
0s
1v
1O
0R
1:
0C
0U
0^
1p
0K
1T
1]
b10001010 %
b10001010 *
b11110010 $
b11110010 )
b11001 &
#276000
b101111100 w
b11110010 '
b10001010 (
#286000
1u
0G
1r
0E
1"
b11001 !
b11001 .
0k
1h
15
0;
0b
b11001 +
0t
b11000000 ,
1q
0j
1m
14
0@
0a
1s
0v
0:
1U
1g
10
09
0T
0]
0o
b11011000 %
b11011000 *
b1000001 $
b1000001 )
b11010 &
#287000
b100011001 w
b1000001 '
b11011000 (
#297000
1l
1i
1_
1c
1"
1`
1q
1V
0t
1u
0Y
1Z
1r
1W
b1 !
b1 .
0k
1h
0P
b11111000 ,
1M
b1 +
0b
1j
0m
0O
1R
1a
11
0U
0g
00
1K
1T
1]
b10001001 %
b10001001 *
b1111000 $
b1111000 )
b11011 &
#298000
b100000001 w
b1111000 '
b10001001 (
#308000
1Q
1`
1N
1V
1D
0Y
1Z
1H
1W
1E
b10100001 !
b10100001 .
0G
0P
1M
1b
0c
b11111110 ,
1;
b10100001 +
1t
0u
1F
1O
0R
0a
1d
1@
0s
1v
01
1:
1C
0L
1U
1^
10
19
0T
1o
b10110110 %
b10110110 *
b11101011 $
b11101011 )
b11100 &
#309000
b110100001 w
b11101011 '
b10110110 (
#319000
0t
0r
0h
0`
1k
0l
0V
0i
b1110100 !
b1110100 .
1Y
0Z
05
1G
0H
b1110100 +
1b
0c
b10001110 ,
0_
0X
04
0F
1I
1a
0d
1L
0U
00
1B
0K
0]
b10101110 %
b10101110 *
b11000110 $
b11000110 )
b11101 &
#320000
b101110100 w
b11000110 '
b10101110 (
#330000
1`
0N
0E
1V
1i
0"
b11100110 !
b11100110 .
1G
0H
0D
1t
0q
1>
0;
0P
0Q
0Y
1Z
1b
b111000 ,
1_
b11100110 +
1k
1F
0I
1s
0v
1=
0@
0O
1R
1X
0a
1d
0j
0C
0p
09
1K
1T
1]
0f
b101010 %
b101010 *
b10111100 $
b10111100 )
b11110 &
#331000
b11100110 w
b10111100 '
b101010 (
#341000
0`
1E
0V
1;
1Y
0Z
0r
0>
1?
0W
0h
1<
0i
b1111100 !
b1111100 .
1P
0M
1k
0l
12
1G
1b
0c
b11 ,
0_
b1111100 +
0t
1O
0R
1j
17
0F
1a
0d
0s
11
0:
0L
1U
1g
10
19
0B
0T
0]
0o
b1110001 %
b1110001 *
b1011 $
b1011 )
b11111 &
#342000
b1111100 w
b1011 '
b1110001 (
#352000
1W
1M
0P
1Q
1N
b11010100 !
b11010100 .
1Y
0b
b1111 ,
1D
b11010100 +
1t
0X
0a
1I
1s
1:
1C
1L
0U
0^
09
1B
0K
1o
b1001111 %
b1001111 *
b10000101 $
b10000101 )
b100000 &
#353000
b11010100 w
b10000101 '
b1001111 (
#363000
1b
0<
0N
1`
1i
b1110101 !
b1110101 .
15
02
1k
0>
0?
0D
0P
0Q
1V
b111010 ,
1_
b1110101 +
0t
14
07
0j
0=
1@
0I
0O
1R
1[
1d
0s
01
0C
1U
1^
0g
19
0B
1K
1T
1]
0o
b111010 %
b111010 *
b111011 $
b111011 )
b100001 &
#364000
b1110101 w
b111011 '
b111010 (
#374000
1t
0G
1Y
1Q
1r
0E
1W
1i
1N
b10010011 !
b10010011 .
1h
1>
0;
0P
1M
0b
1c
1_
b1111100 ,
1D
b10010011 +
0k
1l
1=
0@
1O
0R
1a
0d
1I
1j
11
0:
1C
0L
0^
00
1B
1f
b10101 %
b10101 *
b1111110 $
b1111110 )
b100010 &
#375000
b10010011 w
b1111110 '
b10101 (
#385000
0Y
0W
0M
1P
0Q
1<
0N
1"
b11001010 !
b11001010 .
1k
0l
05
12
b11001010 +
1>
0D
b11110001 ,
1q
0j
1m
04
17
0=
0I
1v
0C
1L
1g
1p
10
09
0B
0K
1o
b11011001 %
b11011001 *
b11110001 $
b11110001 )
b100011 &
#386000
b111001010 w
b11110001 '
b11011001 (
#396000
0Y
0W
0M
1P
0Q
0N
0k
0D
0i
0H
0_
0E
1b
0c
0<
0;
0`
0"
b10101110 !
b10101110 .
1G
02
b10101110 +
1>
0?
0V
b1000000 ,
0q
1F
07
1=
0[
0v
01
1C
0U
0p
00
19
0T
0o
b1001100 %
b1001100 *
b1100010 $
b1100010 )
b100100 &
#397000
b10101110 w
b1100010 '
b1001100 (
#407000
1`
1V
1Z
0t
1E
1<
1N
1W
0r
1"
b101110 !
b101110 .
1>
1;
12
1G
1D
1P
1M
0Y
b101110 +
1b
0h
b10011111 ,
1q
0=
1@
17
0F
1I
0O
1R
1X
0a
0m
1v
11
1:
0g
1p
10
1B
1K
1T
0]
0f
1o
b10001111 %
b10001111 *
b10011111 $
b10011111 )
b100101 &
#408000
b100101110 w
b10011111 '
b10001111 (
#418000
1t
1r
1h
1l
0W
0<
0E
0N
1i
b10101111 !
b10101111 .
1P
0Q
0M
0Y
0Z
15
02
1>
0?
0;
1G
0H
0D
b11110000 ,
1_
b10101111 +
0k
1O
0R
0X
1[
14
07
1=
0@
1F
0I
1d
1j
0L
1U
1^
00
09
0B
1]
1f
b10110111 %
b10110111 *
b11111000 $
b11111000 )
b100110 &
#419000
b110101111 w
b11111000 '
b10110111 (
#429000
0r
0h
1Y
1k
0l
1W
1N
0i
0"
b11111011 !
b11111011 .
1P
1M
1t
0u
0q
b11111011 +
0G
1D
b11100 ,
0_
0O
1R
1s
0v
0F
1I
0d
01
0:
1L
0^
1g
0p
10
19
1B
0]
0f
b1011100 %
b1011100 *
b10011111 $
b10011111 )
b100111 &
#430000
b11111011 w
b10011111 '
b1011100 (
#440000
1G
1E
1;
0>
1?
1b
0P
1<
1`
0N
b11100100 !
b11100100 .
05
12
b11100100 +
0Y
1Z
1V
b11011 ,
0D
04
17
1X
0[
0I
11
0C
0U
0g
1p
0B
1f
0o
b10001001 %
b10001001 *
b1011011 $
b1011011 )
b101000 &
#441000
b11100100 w
b1011011 '
b10001001 (
#451000
0b
0`
0V
1"
1q
0G
1Y
0Z
0t
1u
0E
0<
0W
1r
b11001 !
b11001 .
0;
15
02
1P
0M
0k
b11000000 ,
1h
b11001 +
0>
0?
14
07
1O
0R
0j
1m
0=
01
0L
1U
1g
09
0T
b11010000 %
b11010000 *
b1001001 $
b1001001 )
b101001 &
#452000
b100011001 w
b1001001 '
b11010000 (
#462000
1N
1D
1H
1E
1;
1?
1b
1<
1`
b101000 !
b101000 .
05
12
0>
0G
1P
b101000 +
0Y
b11010111 ,
1V
04
17
1=
1F
0O
0X
1[
11
0p
19
1B
0K
1T
1o
b1010001 %
b1010001 *
b11010111 $
b11010111 )
b101010 &
#463000
b100101000 w
b11010111 '
b1010001 (
#473000
0E
0"
1Z
0;
0q
1W
1b
1>
0?
1t
0u
1M
1`
0<
0r
b10100010 !
b10100010 .
0G
0H
0P
1Q
b10100010 +
0Y
1V
02
b11100 ,
0h
0F
1I
1O
1X
0[
07
0m
01
1C
1L
0U
0g
00
0f
b1100 %
b1100 *
b10010110 $
b10010110 )
b101011 &
#474000
b10100010 w
b10010110 '
b1100 (
#484000
0W
0M
0b
1P
0Q
0`
0N
0V
1r
1"
b10001010 !
b10001010 .
1t
1q
0D
b10001010 +
0Y
0Z
b11000000 ,
1h
0s
1v
0I
0X
1m
0C
1g
1p
0B
0T
1f
b11001000 %
b11001000 *
b11000010 $
b11000010 )
b101100 &
#485000
b110001010 w
b11000010 '
b11001000 (
#495000
1G
1Y
1E
1W
1;
1M
1t
0>
1?
0P
1Q
1b
1l
1r
1<
1N
1`
1i
0"
b10110100 !
b10110100 .
b10110100 +
0k
1h
12
1D
1V
1_
b1111111 ,
0q
1j
0m
17
1I
1[
1d
0v
11
1C
1U
1^
0g
0p
10
1B
1T
1]
0o
b111101 %
b111101 *
b1110111 $
b1110111 )
b101101 &
#496000
b10110100 w
b1110111 '
b111101 (
#506000
1Y
1t
1W
1r
1M
1h
0P
1Q
0k
1l
0<
1N
1i
b10010000 !
b10010000 .
0>
0?
02
0G
1H
1D
b10010000 +
0b
1c
b1111110 ,
1_
0=
1@
07
1F
0I
1a
0d
01
1:
1g
00
0B
0]
0f
b1111110 %
b1111110 *
b10010 $
b10010 )
b101110 &
#507000
b10010000 w
b10010 '
b1111110 (
#517000
0N
0D
1>
1G
0H
1<
0E
1`
b10100110 !
b10100110 .
12
0;
0P
0Q
0Y
1Z
b1111001 ,
1V
b10100110 +
1b
0c
17
0@
0O
1R
1X
0[
0a
1d
11
0:
0C
0g
10
09
1B
1K
0T
1]
1f
b111001 %
b111001 *
b1101101 $
b1101101 )
b101111 &
#518000
b10100110 w
b1101101 '
b111001 (
#528000
1Q
1N
0r
1D
0h
0"
0G
1H
1k
0l
1W
0q
1E
0i
b11110010 !
b11110010 .
0P
1M
1t
0u
1;
b11110010 +
1Y
0Z
b11111 ,
0_
1O
0R
1s
1@
0X
1[
0d
1:
0L
0^
1g
1p
19
1T
0]
0f
b11010011 %
b11010011 *
b11111 $
b11111 )
b110000 &
#529000
b11110010 w
b11111 '
b11010011 (
#539000
0"
0q
0W
1t
0u
0M
0r
1P
0Q
0h
0N
1k
0l
0D
0>
0i
1G
0H
0<
0_
0E
0`
b11111101 !
b11111101 .
15
02
1b
0c
0;
b11111101 +
1Y
0Z
b0 ,
0V
14
07
1a
0@
1X
0[
01
0:
1L
1^
0p
09
0K
0T
1o
b1111000 %
b1111000 *
b10000101 $
b10000101 )
b110001 &
#540000
b11111101 w
b10000101 '
b1111000 (
#550000
1E
1`
1;
1V
1?
0Y
1Z
1<
1W
1r
b10100100 !
b10100100 .
05
12
1b
0>
1G
0P
1M
0k
b1011011 ,
1h
b10100100 +
1t
04
17
0a
1=
0F
0O
1R
0j
1m
0s
11
0U
0^
19
0B
1K
1T
1f
0o
b1001001 %
b1001001 *
b1011011 $
b1011011 )
b110010 &
#551000
b10100100 w
b1011011 '
b1001001 (
#561000
1P
1N
1k
0t
0<
1D
1i
0r
b1101001 !
b1101001 .
15
02
0>
0?
b1101001 +
0G
1H
1_
b111110 ,
0h
14
07
0=
1@
1F
1d
0m
01
1:
1^
0g
1B
1]
0f
b101010 %
b101010 *
b111111 $
b111111 )
b110011 &
#562000
b1101001 w
b111111 '
b101010 (
#572000
0b
0`
0N
0"
0q
0V
0D
0u
1Y
0Z
1G
0H
0r
0W
0E
0i
b11011110 !
b11011110 .
0h
1P
0Q
0M
1t
05
1>
0;
b0 ,
0_
b11011110 +
1k
0l
1O
0R
1s
04
1=
0@
0d
1j
1C
0L
0^
1p
00
09
0B
0]
1f
b10000110 %
b10000110 *
b1011000 $
b1011000 )
b110100 &
#573000
b11011110 w
b1011000 '
b10000110 (
#583000
1b
1`
1V
0Y
1Z
1W
1N
1"
b101010 !
b101010 .
1P
1M
0G
1D
0k
b101010 +
0t
b10011100 ,
1q
0O
1R
0F
1I
0j
0s
1v
0:
1L
1U
19
1B
0T
0f
1o
b10011100 %
b10011100 *
b10001110 $
b10001110 )
b110101 &
#584000
b100101010 w
b10001110 '
b10011100 (
